Makefile
README.md
env_allowlist.txt
ampy_config/__init__.py
ampy_config/cli.py
ampy_config/layering.py
ampy_config/bus/ampy_bus.py
ampy_config/bus/nats_bus.py
ampy_config/control/agent.py
ampy_config/control/events.py
ampy_config/obs/audit.py
ampy_config/obs/logging.py
ampy_config/obs/metrics.py
ampy_config/sdk/runtime.py
ampy_config/secrets/base.py
ampy_config/secrets/registry.py
config/defaults.yaml
examples/dev.yaml
examples/paper.yaml
examples/prod.yaml
examples/service_demo.py
go/ampyconfig/Makefile
go/ampyconfig/README.md
schema/ampy-config.schema.json
tools/validate.py
ampy_config-1.1.5.dist-info/METADATA
ampy_config-1.1.5.dist-info/WHEEL
ampy_config-1.1.5.dist-info/entry_points.txt
ampy_config-1.1.5.dist-info/licenses/LICENSE
ampy_config-1.1.5.dist-info/RECORD
