Metadata-Version: 2.4
Name: ampy-config
Version: 1.1.5
Summary: Typed configuration & secrets facade for AmpyFin (layering, validation, secrets, control-plane)
Author: AmpyFin contributors
License: Apache-2.0
License-File: LICENSE
Keywords: ampyfin,config,secrets,trading,yaml
Requires-Python: >=3.10
Requires-Dist: jsonschema>=4.21
Requires-Dist: pyyaml>=6.0
Provides-Extra: aws
Requires-Dist: boto3>=1.34; extra == 'aws'
Provides-Extra: bus
Requires-Dist: ampy-bus[nats]>=0.1.0; extra == 'bus'
Provides-Extra: gcp
Requires-Dist: google-cloud-secret-manager>=2.20; extra == 'gcp'
Provides-Extra: test
Requires-Dist: pytest-asyncio>=0.23; extra == 'test'
Requires-Dist: pytest>=8.0; extra == 'test'
Provides-Extra: vault
Requires-Dist: hvac>=2.1; extra == 'vault'
